image_to_sticker/__init__.py
image_to_sticker/image_to_sticker.py
image_to_sticker/models/__init__.py
image_to_sticker/models/borderizer.py
image_to_sticker/models/isnet.py
image_to_sticker-2024.3.13.0.dist-info/LICENSE
image_to_sticker-2024.3.13.0.dist-info/METADATA
image_to_sticker-2024.3.13.0.dist-info/WHEEL
image_to_sticker-2024.3.13.0.dist-info/top_level.txt
image_to_sticker-2024.3.13.0.dist-info/zip-safe
image_to_sticker-2024.3.13.0.dist-info/RECORD
