Metadata-Version: 2.1
Name: image-to-sticker
Version: 2024.3.13.0
Summary: ImageToSticker: convert your image into a sticker
Home-page: UNKNOWN
Author: Sergei Belousov aka BeS
Author-email: sergei.o.belousov@gmail.com
License: UNKNOWN
Platform: UNKNOWN
Classifier: Programming Language :: Python :: 3
License-File: LICENSE
Requires-Dist: huggingface-hub >=0.17.3
Requires-Dist: numpy >=1.23.4
Requires-Dist: opencv-python >=4.8.1.78
Requires-Dist: torch >=2.0.0
Requires-Dist: torchvision >=0.16.1
